autoenum/__init__.py
autoenum-1.1.1.dist-info/METADATA
autoenum-1.1.1.dist-info/WHEEL
autoenum-1.1.1.dist-info/licenses/LICENSE
autoenum-1.1.1.dist-info/RECORD
