Metadata-Version: 2.4
Name: autoenum
Version: 1.1.1
Summary: A fuzzy-matched, Pydantic-compatible enum library for Python 3.
Author-email: Abhishek Divekar <adivekar@utexas.edu>
License-File: LICENSE
Classifier: Operating System :: OS Independent
Classifier: Programming Language :: Python :: 3
Requires-Python: >=3.10.9
Requires-Dist: requests
